{
    "course_code": "JS 497R",
    "course_title": "Directed Reading In Jewish Studies",
    "credit_hours": "1-4",
    "seats": "Seats: Maximum Enrollment: 999 / Seats Avail: 999",
    "waitlist_total": null,
    "grading_mode": "Student Option",
    "enrollment_status": "Open",
    "instruction_method": "In Person",
    "typically_offered": "Fall and Spring",
    "requirement_designation": null,
    "permission": null,
    "dates": "2022-08-24 through 2022-12-06",
    "class_notes": null,
    "course_description": "Prerequisite: consent of instructor. Specific readings for each student are decided upon in consultation with a member of the faculty.",
    "prerequisites": null,
    "instructors": null,
    "schedule_location": null,
    "course_resources": null,
    "sections": "Class Nbr: 1413, Section #: 1, Type: SUP, Campus: ATL, Meets: Does Not Meet, Instructor: Staff, Status: Open",
    "date_accessed": "2024-03-30"
}