{
    "course_code": "PE_OX 106",
    "course_title": "Circuit and Plyometric Training",
    "credit_hours": "1",
    "seats": "Seats: Maximum Enrollment: 16 / Seats Avail: 4Waitlist Total: 0 of 6",
    "waitlist_total": ": 0 of 6",
    "grading_mode": "Student Option",
    "enrollment_status": "Open",
    "instruction_method": "In Person",
    "typically_offered": "Fall and Spring",
    "requirement_designation": "Principles of Physical Fitness",
    "permission": null,
    "dates": "2023-01-10 through 2023-04-24",
    "class_notes": null,
    "course_description": "A basic health course using a variety of physical activities to experience and practice the principles of fitness related to cardiovascular conditioning, muscular strength and resistance, and plyometric training.",
    "prerequisites": null,
    "instructors": "Opal Duncan - Primary Instructor",
    "schedule_location": "MW 10am-11:15am in Weight Room",
    "course_resources": null,
    "sections": "Class Nbr: 4288, Section #: 1, Type: PE, Campus: OXF, Meets: MW 10-11:15a, Instructor: O. Duncan, Status: Open",
    "date_accessed": "2024-03-30"
}