{
    "course_code": "LAW 590E",
    "course_title": "Analysis, Research, and Communications for Non-Lawyers",
    "credit_hours": "3",
    "seats": "Seats: Varies by section",
    "waitlist_total": null,
    "grading_mode": "Graded",
    "enrollment_status": "Open",
    "instruction_method": "Distance Learning",
    "typically_offered": null,
    "requirement_designation": null,
    "permission": null,
    "dates": "2021-10-19 through 2021-12-06",
    "class_notes": "JM students only",
    "course_description": "This course will provide an introduction to legal analysis, research and effective legal writing.Students will be introduced to the fundamentals of legal analysis and the structure of legal information.Students will learn how to navigate multiple legal resources to discover legal authority appropriate for different types of legal analyses and communications. Students will apply the concepts of effective legal analysis to produce legal analyses appropriate for their audiences and work situations.",
    "prerequisites": null,
    "instructors": null,
    "schedule_location": null,
    "course_resources": null,
    "sections": "Class Nbr: 4788, Section #: 001, Type: LEC, Campus: ONLIN, Meets: Meets Online, Instructor: A. Thornton, Status: Open\nClass Nbr: 4792, Section #: 002, Type: LEC, Campus: ONLIN, Meets: Meets Online, Instructor: O. Marbutt, Status: Open",
    "date_accessed": "2024-03-30"
}