{
    "course_code": "SOC 213",
    "course_title": "Sociology of the Family",
    "credit_hours": "3-4",
    "seats": "Seats: Maximum Enrollment: 0 / Seats Avail: 0",
    "waitlist_total": null,
    "grading_mode": "Student Option",
    "enrollment_status": "Closed",
    "instruction_method": "In Person",
    "typically_offered": "Fall",
    "requirement_designation": "History, Society, Cultures",
    "permission": null,
    "dates": "2021-08-25 through 2021-12-07",
    "class_notes": null,
    "course_description": "Organization, functions, and present status of the family, primarily in the United States. Problems of partner selection and marital adjustment treated on the basis of recent and current research in the field.",
    "prerequisites": null,
    "instructors": null,
    "schedule_location": null,
    "course_resources": null,
    "sections": "Class Nbr: This section is full 6486, Section #: 9000, Type: LEC, Campus: ATL, Meets: Does Not Meet, Instructor: Staff, Status: Closed",
    "date_accessed": "2024-03-30"
}