{
    "course_code": "ST 658",
    "course_title": "Theology of James Cone",
    "credit_hours": "3",
    "seats": "Seats: Maximum Enrollment: 27 / Seats Avail: 14",
    "waitlist_total": null,
    "grading_mode": "Graded",
    "enrollment_status": "Open",
    "instruction_method": "In Person",
    "typically_offered": "Irregularly",
    "requirement_designation": null,
    "permission": null,
    "dates": "2023-01-09 through 2023-04-24",
    "class_notes": "(ON CAMPUS; prerequisite ST 501 or permission of the instructor)",
    "course_description": "This course is designed to provide an in-depth study of James Cone¿s theology through reading the key texts written over the course of his career his career. In addition to seeking to understanding Cone¿s thought in its North American context, attention will also be given to its relation to other contextualized theologies.",
    "prerequisites": "ST 501 or equivalent transfer credit as prerequisite.",
    "instructors": "Ian McFarland - Primary Instructor",
    "schedule_location": "T 6pm-9pm in Rita Anne Rollins Building_549",
    "course_resources": null,
    "sections": "Class Nbr: 5682, Section #: 1, Type: SEM, Campus: ATL, Meets: T 6-9p, Instructor: I. McFarland, Status: Open",
    "date_accessed": "2024-03-30"
}