{
    "course_code": "BUS 536",
    "course_title": "Washington Campus",
    "credit_hours": "Varies by section",
    "seats": "Seats: Maximum Enrollment: 66 / Seats Avail: 66Waitlist Total: 0",
    "waitlist_total": ": 0",
    "grading_mode": "Graded",
    "enrollment_status": "Open",
    "instruction_method": "In Person",
    "typically_offered": "Fall and Spring",
    "requirement_designation": null,
    "permission": null,
    "dates": "Varies by section",
    "class_notes": null,
    "course_description": "An intensive, experiential residency course that brings together students & policy makers & executives who teach how government works & how public policy is made; how specific organizations & industries are affected; & how public affairs & public policy can be effectively & ethically managed .This course is delivered by The Washington Campus, a non-partisan, non-profit, higher education consortium & managed by the faculty of record.",
    "prerequisites": "Varies by section",
    "instructors": null,
    "schedule_location": null,
    "course_resources": null,
    "sections": "Class Nbr: 4822, Section #: 2101, Type: LEC, Campus: ATL, Meets: Does Not Meet, Instructor: Lord/Conner, Status: Open\nClass Nbr: 4823, Section #: 2201, Type: LEC, Campus: ATL, Meets: Does Not Meet, Instructor: Lord/Conner, Status: Open\nClass Nbr: 5086, Section #: 2202, Type: LEC, Campus: ATL, Meets: Does Not Meet, Instructor: Lord/Conner, Status: Open\nClass Nbr: 4824, Section #: 3201, Type: LEC, Campus: ATL, Meets: Does Not Meet, Instructor: Lord/Ruskin, Status: Open",
    "date_accessed": "2023-10-31"
}