{
    "course_code": "PE 192",
    "course_title": "Beginning Fencing",
    "credit_hours": "1",
    "seats": "Seats: Maximum Enrollment: 18 / Seats Avail: 1Waitlist Total: 0",
    "waitlist_total": ": 0",
    "grading_mode": "Student Option",
    "enrollment_status": "Open",
    "instruction_method": "In Person",
    "typically_offered": "Fall and Spring",
    "requirement_designation": "Physical Education(*)",
    "permission": null,
    "dates": "2023-08-23 through 2023-12-05",
    "class_notes": null,
    "course_description": "This course introduces the student to the Olympic sport of foil fencing. Beginning level offensive and defensive techniques will be taught as well as the rules of competition. Emphasis will be placed on the proper execution of the basic skills and physical conditioning.\n\"",
    "prerequisites": "Students completing PE 292 or equivalent cannot enroll for PE 192. For concerns, please contact the Physical Education department.",
    "instructors": "Terrence Lasker Lasker - Primary Instructor",
    "schedule_location": "TTh 10am-11:15am in Woodruff PE Center Arena Crt 4",
    "course_resources": null,
    "sections": "Class Nbr: 5399, Section #: 1, Type: PE, Campus: ATL, Meets: TTh 10-11:15a, Instructor: T. Lasker, Status: Open",
    "date_accessed": "2024-03-30"
}