{
    "course_code": "NHS 580",
    "course_title": "Human Nutrition I",
    "credit_hours": "6",
    "seats": "Seats: Maximum Enrollment: 10 / Seats Avail: 3",
    "waitlist_total": null,
    "grading_mode": "Graded",
    "enrollment_status": "Open",
    "instruction_method": "In Person",
    "typically_offered": null,
    "requirement_designation": null,
    "permission": null,
    "dates": "2021-08-25 through 2021-12-07",
    "class_notes": "(Letter Grade Only)\n(Prerequisite: One Year Biology and Organic Chemistry)",
    "course_description": null,
    "prerequisites": null,
    "instructors": "Usha Ramakrishnan - Primary Instructor",
    "schedule_location": "MW 8am-9:50am in Grace Crum Rollins TBA\nTTh 9am-9:50am in Grace Crum Rollins TBA",
    "course_resources": null,
    "sections": "Class Nbr: 1022, Section #: 1, Type: LEC, Campus: ATL, Meets: MW 8-9:50a; TTh 9-9:50a, Instructor: U. Ramakrishnan, Status: Open",
    "date_accessed": "2024-03-30"
}