{
    "course_code": "ENVS 499RW",
    "course_title": "Advanced Independent Research",
    "credit_hours": "1-12",
    "seats": "Seats: Maximum Enrollment: 1 / Seats Avail: 0",
    "waitlist_total": null,
    "grading_mode": "Student Option",
    "enrollment_status": "Closed",
    "instruction_method": "In Person",
    "typically_offered": "Fall, Spring, and Summer",
    "requirement_designation": "Continuing Writing Requirement",
    "permission": "Department Consent Required",
    "dates": "2021-08-25 through 2021-12-07",
    "class_notes": null,
    "course_description": "Students design a research project in collaboration with ENVS faculty. Permission required. Intended for students with previous research experience. Fulfills the ENVS Independent Study requirement.",
    "prerequisites": null,
    "instructors": "Gonzalo Vazquez Prokopec - Primary Instructor",
    "schedule_location": null,
    "course_resources": null,
    "sections": "Class Nbr: This section is full 6309, Section #: 1, Type: RSC, Campus: ATL, Meets: Does Not Meet, Instructor: G. Vazquez Prokopec, Status: Closed",
    "date_accessed": "2024-03-30"
}