{
    "course_code": "PSYC 499R",
    "course_title": "Directed Research: Lourenco Lab:Vision, Cogn&Dev.",
    "credit_hours": "1-12",
    "seats": "Seats: Maximum Enrollment: 10 / Seats Avail: 7",
    "waitlist_total": null,
    "grading_mode": "Student Option",
    "enrollment_status": "Open",
    "instruction_method": "In Person",
    "typically_offered": "Fall, Spring, and Summer",
    "requirement_designation": null,
    "permission": "Department Consent Required",
    "dates": "2023-01-10 through 2023-04-24",
    "class_notes": null,
    "course_description": "Credit variable. Psychology majors only, registration by permission of faculty supervisor.",
    "prerequisites": null,
    "instructors": "Stella Lourenco - Primary Instructor",
    "schedule_location": null,
    "course_resources": null,
    "sections": "Class Nbr: 5456, Section #: 20, Type: SUP, Campus: ATL, Meets: Does Not Meet, Instructor: S. Lourenco, Status: Open",
    "date_accessed": "2024-03-30"
}