{
    "course_code": "CE 551TPB",
    "course_title": "Con Ed lb for Teaching Parish",
    "credit_hours": "2",
    "seats": "Seats: Varies by section",
    "waitlist_total": null,
    "grading_mode": "Satisfactory/Unsatisfactory",
    "enrollment_status": "Closed",
    "instruction_method": "Varies by section",
    "typically_offered": "Spring",
    "requirement_designation": null,
    "permission": "Varies by section",
    "dates": "2023-01-09 through 2023-04-24",
    "class_notes": "Varies by section",
    "course_description": "First-year MDiv students who are in the Teaching Parish Program may enroll for CE551TPa,b in lieu of CE551a,b. Participants are assigned to student pastor groups in respective districts under the leadership of the teaching parish supervisory pastors, United Methodist ministers who serve as Candler adjunct faculty. Coursework is experiential and collegial in nature, with studentpastors engaging in practice and reflection on a variety of ministerial activities (e.g., preaching, systems analysis, planning, and teaching).",
    "prerequisites": null,
    "instructors": "Thomas Elliott - Primary Instructor",
    "schedule_location": "Varies by section",
    "course_resources": null,
    "sections": "Class Nbr: This section is full 5366, Section #: 1, Type: LEC, Campus: ATL, Meets: M 9a-2p, Instructor: T. Elliott, Status: Closed\nClass Nbr: This section is full 5367, Section #: 10, Type: LEC, Campus: ATL, Meets: M 9a-2p, Instructor: T. Elliott, Status: Closed",
    "date_accessed": "2024-03-30"
}