{
    "course_code": "PE_OX 100",
    "course_title": "Health/Conditioning/Fitness Walking",
    "credit_hours": "1",
    "seats": "Seats: Varies by section",
    "waitlist_total": null,
    "grading_mode": "Student Option",
    "enrollment_status": "Closed",
    "instruction_method": "In Person",
    "typically_offered": "Fall and Spring",
    "requirement_designation": "Principles of Physical Fitness",
    "permission": null,
    "dates": "2021-08-25 through 2021-12-07",
    "class_notes": null,
    "course_description": "A basic health course incorporating a variety of physical activities to increase individuals' cardiovascular fitness. Health concepts will emphasize personal responsibility for the student's well-being. Fitness walking is for students who need low impact cardiovascular fitness.",
    "prerequisites": null,
    "instructors": "Molly McNamara - Primary Instructor",
    "schedule_location": "Varies by section",
    "course_resources": null,
    "sections": "Class Nbr: This section is full 3130, Section #: 1, Type: PE, Campus: OXF, Meets: TTh 10-11:15a, Instructor: M. McNamara, Status: Wait List\nClass Nbr: This section is full 3131, Section #: 2, Type: PE, Campus: OXF, Meets: TTh 8:30-9:45a, Instructor: M. McNamara, Status: Closed",
    "date_accessed": "2024-03-30"
}