{
    "course_code": "ACT 513",
    "course_title": "Managerial Accounting",
    "credit_hours": "3",
    "seats": "Seats: Varies by section",
    "waitlist_total": null,
    "grading_mode": "Graded",
    "enrollment_status": "Varies by section",
    "instruction_method": "Varies by section",
    "typically_offered": null,
    "requirement_designation": null,
    "permission": null,
    "dates": "2024-05-17 through 2024-08-07",
    "class_notes": null,
    "course_description": "Introduction to the concepts, assumptions, and methods underlying managerial accounting, with an emphasis on using accounting information to plan and control a company's operations. Topics include information relevant for decision-making, cost behavior, activity-based costing, pricing, cost-volume-profit analysis, operating budgets and variance analysis, capital budgeting, and performance evaluation.",
    "prerequisites": "Varies by section",
    "instructors": "Jeff Byrne - Primary Instructor",
    "schedule_location": "Varies by section",
    "course_resources": null,
    "sections": "Class Nbr: 1863, Section #: 2101, Type: LEC, Campus: ATL, Meets: W 6:30-9:30p, Instructor: J. Byrne, Status: Open\nClass Nbr: 1987, Section #: 2130, Type: LEC, Campus: ATL, Meets: T 6:30-9:30p, Instructor: J. Byrne, Status: Open\nClass Nbr: This section is full 1988, Section #: 2230, Type: LEC, Campus: ATL, Meets: T 6:30-9:30p, Instructor: J. Byrne, Status: Wait List\nClass Nbr: 1989, Section #: 2630, Type: LEC, Campus: ATL, Meets: T 6:30-9:30p, Instructor: J. Byrne, Status: Open",
    "date_accessed": "2024-03-29"
}