{
    "course_code": "PHYS 598",
    "course_title": "Research Summary",
    "credit_hours": "3",
    "seats": "Seats: Varies by section",
    "waitlist_total": null,
    "grading_mode": "Graded",
    "enrollment_status": "Open",
    "instruction_method": "In Person",
    "typically_offered": "Fall, Spring, and Summer",
    "requirement_designation": null,
    "permission": "Varies by section",
    "dates": "2023-08-23 through 2023-12-05",
    "class_notes": null,
    "course_description": "This course is taken by 2nd-year graduate students in the fall semester, and requires a written literature summary that will introduce the student to their qualifier topic.",
    "prerequisites": null,
    "instructors": null,
    "schedule_location": null,
    "course_resources": null,
    "sections": "Class Nbr: 2066, Section #: 1, Type: LEC, Campus: ATL, Meets: Does Not Meet, Instructor: J. Burton, Status: Open\nClass Nbr: 2067, Section #: 10, Type: LEC, Campus: ATL, Meets: Does Not Meet, Instructor: H. Harutyunyan, Status: Open\nClass Nbr: 2068, Section #: 11, Type: LEC, Campus: ATL, Meets: Does Not Meet, Instructor: K. Davis, Status: Open\nClass Nbr: 2069, Section #: 12, Type: LEC, Campus: ATL, Meets: Does Not Meet, Instructor: I. Nemenman, Status: Open\nClass Nbr: 2070, Section #: 13, Type: LEC, Campus: ATL, Meets: Does Not Meet, Instructor: T. Lian, Status: Open\nClass Nbr: 2071, Section #: 14, Type: LEC, Campus: ATL, Meets: Does Not Meet, Instructor: L. Finzi, Status: Open\nClass Nbr: 2073, Section #: 15, Type: LEC, Campus: ATL, Meets: Does Not Meet, Instructor: M. Kim, Status: Open\nClass Nbr: 2074, Section #: 16, Type: LEC, Campus: ATL, Meets: Does Not Meet, Instructor: N. Vega, Status: Open\nClass Nbr: 2075, Section #: 17, Type: LEC, Campus: ATL, Meets: Does Not Meet, Instructor: D. Sussman, Status: Open\nClass Nbr: 2076, Section #: 18, Type: LEC, Campus: ATL, Meets: Does Not Meet, Instructor: K. Warncke, Status: Open\nClass Nbr: 2077, Section #: 19, Type: LEC, Campus: ATL, Meets: Does Not Meet, Instructor: J. Rieser, Status: Open\nClass Nbr: 2078, Section #: 2, Type: LEC, Campus: ATL, Meets: Does Not Meet, Instructor: E. Weeks, Status: Open\nClass Nbr: 2079, Section #: 20, Type: LEC, Campus: ATL, Meets: Does Not Meet, Instructor: D. Weissman, Status: Open\nClass Nbr: 2080, Section #: 21, Type: LEC, Campus: ATL, Meets: Does Not Meet, Instructor: W. Benalcazar, Status: Open\nClass Nbr: 2082, Section #: 22, Type: LEC, Campus: ATL, Meets: Does Not Meet, Instructor: J. Burton, Status: Open\nClass Nbr: 5854, Section #: 23, Type: LEC, Campus: ATL, Meets: Does Not Meet, Instructor: K. Salaita, Status: Open\nClass Nbr: 2083, Section #: 3, Type: LEC, Campus: ATL, Meets: Does Not Meet, Instructor: A. Srivastava, Status: Open\nClass Nbr: 2085, Section #: 4, Type: LEC, Campus: ATL, Meets: Does Not Meet, Instructor: C. Roth, Status: Open\nClass Nbr: 2086, Section #: 5, Type: LEC, Campus: ATL, Meets: Does Not Meet, Instructor: G. Berman, Status: Open\nClass Nbr: 2088, Section #: 6, Type: LEC, Campus: ATL, Meets: Does Not Meet, Instructor: S. Urazhdin, Status: Open\nClass Nbr: 2089, Section #: 7, Type: LEC, Campus: ATL, Meets: Does Not Meet, Instructor: K. Warncke, Status: Open\nClass Nbr: 2090, Section #: 8, Type: LEC, Campus: ATL, Meets: Does Not Meet, Instructor: L. Santos, Status: Open\nClass Nbr: 2091, Section #: 9, Type: LEC, Campus: ATL, Meets: Does Not Meet, Instructor: S. Boettcher, Status: Open",
    "date_accessed": "2024-03-30"
}