{
    "course_code": "OAM 432",
    "course_title": "Negotiations",
    "credit_hours": "3",
    "seats": "Seats: Varies by section",
    "waitlist_total": null,
    "grading_mode": "Graded",
    "enrollment_status": "Varies by section",
    "instruction_method": "In Person",
    "typically_offered": "Fall and Spring",
    "requirement_designation": null,
    "permission": null,
    "dates": "2022-01-11 through 2022-04-25",
    "class_notes": null,
    "course_description": "Offers students an opportunity to develop negotiation skills for a global business environment. Students learn to manage conflicts with competence, fairness, and sensitivity. The course relies heavily on simulations to promote learning by doing. It provides a low-risk setting with individual feedback to help students evolve an effective negotiating style that feels natural.",
    "prerequisites": "Varies by section",
    "instructors": null,
    "schedule_location": "Varies by section",
    "course_resources": null,
    "sections": "Class Nbr: 1078, Section #: 1101, Type: LEC, Campus: ATL, Meets: TTh 10-11:15a, Instructor: J. Jo, Status: Open\nClass Nbr: This section is full 1079, Section #: 1102, Type: LEC, Campus: ATL, Meets: TTh 1-2:15p, Instructor: J. Jo, Status: Wait List\nClass Nbr: 6437, Section #: 1109, Type: LEC, Campus: ATL, Meets: Does Not Meet, Instructor: J. Billetdeaux, Status: Open",
    "date_accessed": "2024-03-30"
}