{
    "course_code": "NRSG 544D",
    "course_title": "Advanced Health Assessment Across the Lifespan",
    "credit_hours": "3",
    "seats": "Seats: Varies by section",
    "waitlist_total": null,
    "grading_mode": "Graded",
    "enrollment_status": "Open",
    "instruction_method": "Distance Learning",
    "typically_offered": "Fall and Spring",
    "requirement_designation": null,
    "permission": null,
    "dates": "2023-08-23 through 2023-12-05",
    "class_notes": "Varies by section",
    "course_description": "Students will assess/interpret/report pertinent findings on the history and physical exam. An emphasis on clinical decision-making, selection/interpretation of diagnostic tests; and hands-on practice of common procedures is included.",
    "prerequisites": null,
    "instructors": null,
    "schedule_location": null,
    "course_resources": null,
    "sections": "Class Nbr: 5177, Section #: 1, Type: LEC, Campus: ONLIN, Meets: Meets Online, Instructor: E. Downes, Status: Open\nClass Nbr: 6748, Section #: 4, Type: LEC, Campus: ONLIN, Meets: Meets Online, Instructor: J. Adamski, Status: Open",
    "date_accessed": "2024-03-30"
}