{
    "course_code": "HPM 575",
    "course_title": "Capstone-Advanced Topics in Policy Analysis",
    "credit_hours": "3",
    "seats": "Seats: Maximum Enrollment: 65 / Seats Avail: 13",
    "waitlist_total": null,
    "grading_mode": "Graded",
    "enrollment_status": "Open",
    "instruction_method": "Distance Learning",
    "typically_offered": "Spring",
    "requirement_designation": null,
    "permission": null,
    "dates": "2021-01-25 through 2021-05-05",
    "class_notes": "This is a synchronous online class.  HPM students only.",
    "course_description": "Prerequisites: HPM 501, HPM 510, HPM 521, HPM 522, HPM 523, HPM 561 or 557 and HPM 576. This class will teach students how to conduct public health policy analyses that examine options to address emerging issues, conduct analysis of the options and communicate recommendations.",
    "prerequisites": "This class is for students enrolled in the HPM program only.",
    "instructors": "Kenneth E Thorpe - Primary Instructor",
    "schedule_location": "M 9:15am-12:05pm in ONLINE",
    "course_resources": null,
    "sections": "Class Nbr: 4533, Section #: 1, Type: SEM, Campus: ATL, Meets: M 9:15a-12:05p, Instructor: Thorpe/Boualam, Status: Open",
    "date_accessed": "2024-03-30"
}