{
    "course_code": "MATH 485",
    "course_title": "Topics in Mathematics: Convex Optimization",
    "credit_hours": "3",
    "seats": "Seats: Maximum Enrollment: 35 / Seats Avail: 28Waitlist Total: 0",
    "waitlist_total": ": 0",
    "grading_mode": "Student Option",
    "enrollment_status": "Open",
    "instruction_method": "In Person",
    "typically_offered": null,
    "requirement_designation": null,
    "permission": "Department Consent Required",
    "dates": "2022-08-24 through 2022-12-06",
    "class_notes": "Permission required for enrollment. Please contact Taylr Tuggle (tatuggl@emory.edu) for permission into this course.\nMATH 211 or PHYS 211 or MATH_OX 211 or MATH 276) and (MATH 221 or MATH_OX 221 or MATH 321) and (MATH 250 or MATH_OX 250 or MATH 276) and CS170 or equivalent transfer credit as prerequisite",
    "course_description": "Rotating topics in mathematics. May be repeated for credit when the topic varies. Pre and co requisites depend on the topic offered.",
    "prerequisites": null,
    "instructors": "Lars Ruthotto - Primary Instructor",
    "schedule_location": "MW 2:30pm-3:45pm in Math & Science Center - W301",
    "course_resources": null,
    "sections": "Class Nbr: 3830, Section #: 1, Type: LEC, Campus: ATL, Meets: MW 2:30-3:45p, Instructor: L. Ruthotto, Status: Open",
    "date_accessed": "2024-03-30"
}