{
    "course_code": "PSYC 211",
    "course_title": "Childhood Psychopathology",
    "credit_hours": "3",
    "seats": "Seats: Maximum Enrollment: 60 / Seats Avail: 4Waitlist Total: 0",
    "waitlist_total": ": 0",
    "grading_mode": "Student Option",
    "enrollment_status": "Open",
    "instruction_method": "In Person",
    "typically_offered": "Fall",
    "requirement_designation": "Social Sciences(*)",
    "permission": null,
    "dates": "2024-01-17 through 2024-04-29",
    "class_notes": "Prior completion of PSYC 110, or PSYC 111, or AP/IB credit in psychology.",
    "course_description": "Description, classification, causal factors, and treatment approaches of abnormal behavior in children and adolescents.",
    "prerequisites": null,
    "instructors": "Patricia Brennan - Primary Instructor",
    "schedule_location": "TTh 10am-11:15am in New Psyc Bldg 230 (36 Eagle Ro",
    "course_resources": "https://emory.bncollege.com/course-material-listing-page?utm_campaign=storeId=65062_langId=-1_courseData=BN%20at%20Emory_PSYC_211_1_W24&utm_source=wcs&utm_medium=registration_integration",
    "sections": "Class Nbr: 3615, Section #: 1, Type: LEC, Campus: ATL, Meets: TTh 10-11:15a, Instructor: P. Brennan, Status: Open",
    "date_accessed": "2024-03-31"
}