{
    "course_code": "NBB 424",
    "course_title": "Medical Neuropathology",
    "credit_hours": "3",
    "seats": "Seats: Maximum Enrollment: 28 / Seats Avail: 15Waitlist Total: 0",
    "waitlist_total": ": 0",
    "grading_mode": "Student Option",
    "enrollment_status": "Open",
    "instruction_method": "In Person",
    "typically_offered": "Spring",
    "requirement_designation": "Science, Nature, Technology",
    "permission": null,
    "dates": "2024-01-17 through 2024-04-29",
    "class_notes": null,
    "course_description": "The primary focus of this course will be to provide an overview of the neuroanatomical foundations of selected neurological disorders. The first part of the course will be an introduction to the functional neuroanatomy of the brain, followed by clinical topics.",
    "prerequisites": null,
    "instructors": "Keith Easterling - Primary Instructor",
    "schedule_location": "TTh 4pm-5:15pm in 1462 Clifton Rd 123",
    "course_resources": "https://emory.bncollege.com/course-material-listing-page?utm_campaign=storeId=65062_langId=-1_courseData=BN%20at%20Emory_NBB_424_1_W24&utm_source=wcs&utm_medium=registration_integration",
    "sections": "Class Nbr: 2364, Section #: 1, Type: LEC, Campus: ATL, Meets: TTh 4-5:15p, Instructor: K. Easterling, Status: Open",
    "date_accessed": "2023-10-31"
}