{
    "course_code": "ACT 312B",
    "course_title": "Financial Reporting II",
    "credit_hours": "3",
    "seats": "Seats: Maximum Enrollment: 43 / Seats Avail: 5Waitlist Total: 0",
    "waitlist_total": ": 0",
    "grading_mode": "Graded",
    "enrollment_status": "Open",
    "instruction_method": "In Person",
    "typically_offered": "Spring",
    "requirement_designation": null,
    "permission": null,
    "dates": "2022-01-11 through 2022-04-25",
    "class_notes": null,
    "course_description": "Second of two courses examining the foundations of financial accounting and reporting. Accounting issues are considered from the point of view of the preparer, auditor, and user of financial statements. Topics include US and international financial reporting standards for operating and contingent liabilities, debt, leases, shareholders' equity, dilutive securities, marketable securities, investments in affiliates, income taxes, retirement plans, accounting changes and errors, and the statement of cash flows.",
    "prerequisites": "ACT 312A or equivalent transfer credit as prerequisite.This section is reserved for students in the BBA program.",
    "instructors": "Allison Kays - Primary Instructor",
    "schedule_location": "MW 1pm-2:15pm in Goizueta Foundation Ctr W300",
    "course_resources": null,
    "sections": "Class Nbr: 1032, Section #: 1143, Type: LEC, Campus: ATL, Meets: MW 1-2:15p, Instructor: A. Kays, Status: Open",
    "date_accessed": "2024-03-30"
}