{
    "course_code": "KRN 201",
    "course_title": "Intermediate Korean I",
    "credit_hours": "4-6",
    "seats": "Seats: Maximum Enrollment: 0 / Seats Avail: 0",
    "waitlist_total": null,
    "grading_mode": "Student Option",
    "enrollment_status": "Closed",
    "instruction_method": "In Person",
    "typically_offered": "Fall and Spring",
    "requirement_designation": "Humanities, Arts, Language [Foreign Language]",
    "permission": null,
    "dates": "2023-01-10 through 2023-04-24",
    "class_notes": null,
    "course_description": "This course is designed for those who have learned the basics of the Korean language and who want to improve their competence at a higher level. Complex sentences and grammar will be covered while the basics are reviewed.",
    "prerequisites": null,
    "instructors": null,
    "schedule_location": null,
    "course_resources": null,
    "sections": "Class Nbr: This section is full 6811, Section #: 9000, Type: LEC, Campus: ATL, Meets: Does Not Meet, Instructor: Staff, Status: Closed",
    "date_accessed": "2024-03-30"
}